pyrdfj2/__init__.py
pyrdfj2/__version__.py
pyrdfj2/exceptions.py
pyrdfj2/j2_functions.py
pyrdfj2/pyrdfj2.py
pyrdfj2/syntax_builder.py
pyrdfj2-0.0.5.dist-info/LICENSE
pyrdfj2-0.0.5.dist-info/METADATA
pyrdfj2-0.0.5.dist-info/WHEEL
pyrdfj2-0.0.5.dist-info/entry_points.txt
pyrdfj2-0.0.5.dist-info/RECORD
