Metadata-Version: 2.1
Name: pyrdfj2
Version: 0.0.5
Summary: Python wrapper on jinja SPARQL templating
Home-page: https://github.com/vliz-be-opsci/pyrdfj2
License: MIT
Author: Marc Portier
Author-email: marc.portier@gmail.com
Requires-Python: >=3.8.1,<4.0
Classifier: License :: OSI Approved :: MIT License
Classifier: Programming Language :: Python
Classifier: Programming Language :: Python :: 3
Classifier: Programming Language :: Python :: 3.9
Classifier: Programming Language :: Python :: 3.10
Classifier: Programming Language :: Python :: 3.11
Classifier: Programming Language :: Python :: 3.8
Requires-Dist: jinja2
Requires-Dist: python-dateutil
Requires-Dist: uritemplate
Project-URL: Repository, https://github.com/vliz-be-opsci/pyrdfj2
